setup.py
distlh/Binomialdistribution.py
distlh/Gaussiandistribution.py
distlh/Generaldistribution.py
distlh/__init__.py
distlh.egg-info/PKG-INFO
distlh.egg-info/SOURCES.txt
distlh.egg-info/dependency_links.txt
distlh.egg-info/not-zip-safe
distlh.egg-info/top_level.txt