Metadata-Version: 1.0
Name: distlh
Version: 0.1
Summary: Gaussian and Binomial distributions
Home-page: UNKNOWN
Author: Linh Hoang
Author-email: linhht.419@gmail.com
License: UNKNOWN
Platform: UNKNOWN
